subsetsio/__init__.py
subsetsio/models/bar.py
subsetsio/models/chart.py
subsetsio/models/common.py
subsetsio/models/counter.py
subsetsio/models/line.py
subsetsio/models/map.py
subsetsio/models/misc.py
subsetsio/models/scatter.py
subsetsio/models/table.py
subsetsio/models/time.py
subsetsio/models/update.py
subsetsio/sdk.py
subsetsio-0.7.4.dist-info/LICENSE.md
subsetsio-0.7.4.dist-info/METADATA
subsetsio-0.7.4.dist-info/WHEEL
subsetsio-0.7.4.dist-info/RECORD
