Metadata-Version: 2.1
Name: subsetsio
Version: 0.7.4
Summary: Official Python SDK for the Subsets API
Author: Nathan Snellaert
Author-email: nathan@subsets.io
Requires-Python: >=3.11
Classifier: Programming Language :: Python :: 3
Classifier: Programming Language :: Python :: 3.11
Classifier: Programming Language :: Python :: 3.12
Requires-Dist: pandas (>=2.2.3,<3.0.0)
Requires-Dist: pydantic (>=2.10.4,<3.0.0)
Requires-Dist: pytest (>=8.3.4,<9.0.0)
Requires-Dist: requests (>=2.25.0)
Requires-Dist: tenacity (>=9.0.0,<10.0.0)
Requires-Dist: tqdm (>=4.67.1,<5.0.0)
Requires-Dist: typing-extensions (>=4.0.0)
